<?xml version="1.0" encoding="UTF-8"?>
<objects serializationModel="Studio.02.02.00">
	<object class="MixerGroup" id="{10d8d637-6da4-4516-aed5-1f6a071e8c23}">
		<property name="volume">
			<value>3</value>
		</property>
		<property name="name">
			<value>SFX</value>
		</property>
		<relationship name="masters">
			<destination>{8b0f544e-3144-475e-a7d6-a3bfad211d93}</destination>
		</relationship>
		<relationship name="effectChain">
			<destination>{52b04b70-e1d9-4821-8ed0-a9258963bf5b}</destination>
		</relationship>
		<relationship name="panner">
			<destination>{8bee5b6f-99b8-4e91-abe5-93babacb807e}</destination>
		</relationship>
		<relationship name="output">
			<destination>{92e1f325-4f6c-4615-89f3-fb1bd8caf37c}</destination>
		</relationship>
	</object>
	<object class="MixerBusEffectChain" id="{52b04b70-e1d9-4821-8ed0-a9258963bf5b}">
		<relationship name="effects">
			<destination>{f4951e11-c4b3-4c0b-8d44-4bd62cb6df19}</destination>
		</relationship>
	</object>
	<object class="MixerBusPanner" id="{8bee5b6f-99b8-4e91-abe5-93babacb807e}" />
	<object class="MixerBusFader" id="{f4951e11-c4b3-4c0b-8d44-4bd62cb6df19}" />
</objects>
